rmw_fastrtps_shared_cpp/_dummy.cpython-314-x86_64-linux-gnu.so
ros_rmw_fastrtps_shared_cpp-9.3.3.data/data/include/rmw_fastrtps_shared_cpp/rmw_fastrtps_shared_cpp/TypeSupport.hpp
ros_rmw_fastrtps_shared_cpp-9.3.3.data/data/include/rmw_fastrtps_shared_cpp/rmw_fastrtps_shared_cpp/create_rmw_gid.hpp
ros_rmw_fastrtps_shared_cpp-9.3.3.data/data/include/rmw_fastrtps_shared_cpp/rmw_fastrtps_shared_cpp/custom_client_info.hpp
ros_rmw_fastrtps_shared_cpp-9.3.3.data/data/include/rmw_fastrtps_shared_cpp/rmw_fastrtps_shared_cpp/custom_event_info.hpp
ros_rmw_fastrtps_shared_cpp-9.3.3.data/data/include/rmw_fastrtps_shared_cpp/rmw_fastrtps_shared_cpp/custom_participant_info.hpp
ros_rmw_fastrtps_shared_cpp-9.3.3.data/data/include/rmw_fastrtps_shared_cpp/rmw_fastrtps_shared_cpp/custom_publisher_info.hpp
ros_rmw_fastrtps_shared_cpp-9.3.3.data/data/include/rmw_fastrtps_shared_cpp/rmw_fastrtps_shared_cpp/custom_service_info.hpp
ros_rmw_fastrtps_shared_cpp-9.3.3.data/data/include/rmw_fastrtps_shared_cpp/rmw_fastrtps_shared_cpp/custom_subscriber_info.hpp
ros_rmw_fastrtps_shared_cpp-9.3.3.data/data/include/rmw_fastrtps_shared_cpp/rmw_fastrtps_shared_cpp/guid_utils.hpp
ros_rmw_fastrtps_shared_cpp-9.3.3.data/data/include/rmw_fastrtps_shared_cpp/rmw_fastrtps_shared_cpp/init_rmw_context_impl.hpp
ros_rmw_fastrtps_shared_cpp-9.3.3.data/data/include/rmw_fastrtps_shared_cpp/rmw_fastrtps_shared_cpp/listener_thread.hpp
ros_rmw_fastrtps_shared_cpp-9.3.3.data/data/include/rmw_fastrtps_shared_cpp/rmw_fastrtps_shared_cpp/locked_object.hpp
ros_rmw_fastrtps_shared_cpp-9.3.3.data/data/include/rmw_fastrtps_shared_cpp/rmw_fastrtps_shared_cpp/names.hpp
ros_rmw_fastrtps_shared_cpp-9.3.3.data/data/include/rmw_fastrtps_shared_cpp/rmw_fastrtps_shared_cpp/namespace_prefix.hpp
ros_rmw_fastrtps_shared_cpp-9.3.3.data/data/include/rmw_fastrtps_shared_cpp/rmw_fastrtps_shared_cpp/participant.hpp
ros_rmw_fastrtps_shared_cpp-9.3.3.dist-info/METADATA
ros_rmw_fastrtps_shared_cpp-9.3.3.dist-info/WHEEL
ros_rmw_fastrtps_shared_cpp-9.3.3.dist-info/top_level.txt
ros_rmw_fastrtps_shared_cpp-9.3.3.dist-info/RECORD
