Metadata-Version: 2.4
Name: ros-rmw-fastrtps-shared-cpp
Version: 9.3.3
Summary: A ROS package providing shared C++ code for static and dynamic type support in rmw_fastrtps_cpp.
Requires-Dist: ros-rosidl-dynamic-typesupport~=0.3.1
Requires-Dist: ros-rosidl-typesupport-introspection-cpp~=4.9.5
Requires-Dist: ros-rosidl-typesupport-introspection-c~=4.9.5
Requires-Dist: ros-tracetools~=8.6.0
Requires-Dist: ros-fastdds~=3.2.3
Requires-Dist: ros-rmw-security-common~=7.8.2
Requires-Dist: ros-rcutils~=6.9.8
Requires-Dist: ros-rcpputils~=2.13.5
Requires-Dist: ros-rmw~=7.8.2
Requires-Dist: ros-fastcdr~=2.3.3
Requires-Dist: ros-rmw-dds-common~=4.0.0
Dynamic: description
Dynamic: description-content-type
Dynamic: requires-dist
Dynamic: summary
